Metadata-Version: 2.4
Name: seatools-codegen-uv
Version: 1.0.12
Summary: Cookiecutter-seatools-python 代码生成拓展包
Home-page: https://gitee.com/seatools-py/seatools-codegen/tree/uv/
Author: dragons96
Author-email: 521274311@qq.com
License: MIT license
Keywords: seatools,codegen
Classifier: Development Status :: 2 - Pre-Alpha
Classifier: Intended Audience :: Developers
Classifier: License :: OSI Approved :: MIT License
Classifier: Natural Language :: English
Classifier: Programming Language :: Python :: 3.9
Requires-Python: >=3.9
License-File: LICENSE
Requires-Dist: loguru
Requires-Dist: click
Requires-Dist: toml
Dynamic: author
Dynamic: author-email
Dynamic: classifier
Dynamic: home-page
Dynamic: keywords
Dynamic: license
Dynamic: license-file
Dynamic: requires-dist
Dynamic: requires-python
Dynamic: summary
